hanzo_aci/__init__.py
hanzo_aci/cli.py
hanzo_aci/editor/__init__.py
hanzo_aci/editor/config.py
hanzo_aci/editor/editor.py
hanzo_aci/editor/encoding.py
hanzo_aci/editor/exceptions.py
hanzo_aci/editor/file_cache.py
hanzo_aci/editor/history.py
hanzo_aci/editor/md_converter.py
hanzo_aci/editor/prompts.py
hanzo_aci/editor/results.py
hanzo_aci/indexing/locagent/compress.py
hanzo_aci/indexing/locagent/repo/chunk_index/__init__.py
hanzo_aci/indexing/locagent/repo/chunk_index/code_retriever.py
hanzo_aci/indexing/locagent/repo/chunk_index/codeblocks/__init__.py
hanzo_aci/indexing/locagent/repo/chunk_index/codeblocks/codeblocks.py
hanzo_aci/indexing/locagent/repo/chunk_index/codeblocks/module.py
hanzo_aci/indexing/locagent/repo/chunk_index/codeblocks/parser/__init__.py
hanzo_aci/indexing/locagent/repo/chunk_index/codeblocks/parser/comment.py
hanzo_aci/indexing/locagent/repo/chunk_index/codeblocks/parser/create.py
hanzo_aci/indexing/locagent/repo/chunk_index/codeblocks/parser/java.py
hanzo_aci/indexing/locagent/repo/chunk_index/codeblocks/parser/parser.py
hanzo_aci/indexing/locagent/repo/chunk_index/codeblocks/parser/python.py
hanzo_aci/indexing/locagent/repo/chunk_index/codeblocks/parser/queries/__init__.py
hanzo_aci/indexing/locagent/repo/chunk_index/codeblocks/parser/queries/java.scm
hanzo_aci/indexing/locagent/repo/chunk_index/codeblocks/parser/queries/python.scm
hanzo_aci/indexing/locagent/repo/chunk_index/index/__init__.py
hanzo_aci/indexing/locagent/repo/chunk_index/index/code_node.py
hanzo_aci/indexing/locagent/repo/chunk_index/index/epic_split.py
hanzo_aci/indexing/locagent/repo/chunk_index/index/settings.py
hanzo_aci/indexing/locagent/repo/chunk_index/repository.py
hanzo_aci/indexing/locagent/repo/dependency_graph/__init__.py
hanzo_aci/indexing/locagent/repo/dependency_graph/build_graph.py
hanzo_aci/indexing/locagent/repo/dependency_graph/index_retriever.py
hanzo_aci/indexing/locagent/repo/dependency_graph/traverse_graph.py
hanzo_aci/indexing/locagent/results.py
hanzo_aci-0.3.1.dist-info/METADATA
hanzo_aci-0.3.1.dist-info/WHEEL
hanzo_aci-0.3.1.dist-info/RECORD
